gym_cas/__about__.py
gym_cas/__init__.py
gym_cas/algebra.py
gym_cas/config.py
gym_cas/excel.py
gym_cas/globals.py
gym_cas/logarithm.py
gym_cas/ode.py
gym_cas/plot_helpers.py
gym_cas/regression.py
gym_cas/stat_plot.py
gym_cas/stats.py
gym_cas/trigonometry.py
gym_cas/vector.py
gym_cas-1.1.1.dist-info/METADATA
gym_cas-1.1.1.dist-info/WHEEL
gym_cas-1.1.1.dist-info/licenses/LICENSE.txt
gym_cas-1.1.1.dist-info/RECORD
