Metadata-Version: 2.4
Name: gym-cas
Version: 1.1.1
Summary: CAS tools for danish high schools.
Project-URL: Homepage, https://jacs-mat.bitbucket.io/
Author-email: JACS <jacs@zbc.dk>
License-File: LICENSE.txt
Keywords: CAS, Matematik, Math, Gymnasium, HTX
Classifier: Development Status :: 4 - Beta
Classifier: Intended Audience :: Education
Classifier: License :: OSI Approved :: MIT License
Classifier: Operating System :: OS Independent
Classifier: Programming Language :: Python :: 3.10
Classifier: Programming Language :: Python :: 3.11
Classifier: Programming Language :: Python :: 3.12
Classifier: Programming Language :: Python :: 3.13
Classifier: Programming Language :: Python :: 3.14
Classifier: Topic :: Education
Classifier: Topic :: Scientific/Engineering :: Mathematics
Requires-Python: >=3.10
Requires-Dist: matplotlib>=3.7.1
Requires-Dist: numpy>=2.2.6
Requires-Dist: sympy-plot-backends>=4.1.0
Requires-Dist: sympy>=1.14
Provides-Extra: excel
Requires-Dist: openpyxl>=3.1.0; extra == 'excel'
Provides-Extra: test
Requires-Dist: coverage[toml]>=7.3.3; extra == 'test'
Requires-Dist: genbadge[coverage]; extra == 'test'
Requires-Dist: pytest-mock>=3.12.0; extra == 'test'
Requires-Dist: pytest>=7.4.0; extra == 'test'
